tests/__init__.py
tests/test_discovery.py
tests/test_extractors.py
tests/test_integration.py
tests/test_util.py
yaml2helm/__init__.py
yaml2helm/chartwriter.py
yaml2helm/cli.py
yaml2helm/discovery.py
yaml2helm/extractors.py
yaml2helm/report.py
yaml2helm/schema.py
yaml2helm/util.py
yaml2helm/templates/NOTES.txt
yaml2helm/templates/README.md
yaml2helm/templates/_helpers.tpl
yaml2helm-0.1.0.dist-info/licenses/LICENSE
yaml2helm-0.1.0.dist-info/METADATA
yaml2helm-0.1.0.dist-info/WHEEL
yaml2helm-0.1.0.dist-info/entry_points.txt
yaml2helm-0.1.0.dist-info/top_level.txt
yaml2helm-0.1.0.dist-info/RECORD
