Metadata-Version: 2.4
Name: yaml2helm
Version: 0.1.0
Summary: Convert Kubernetes YAML manifests into Helm charts automatically
Author-email: C Turner <chris@example.com>
License-Expression: MIT
Project-URL: Homepage, https://github.com/thecturner/yaml2helm
Project-URL: Repository, https://github.com/thecturner/yaml2helm
Project-URL: Issues, https://github.com/thecturner/yaml2helm/issues
Keywords: kubernetes,helm,yaml,k8s,converter,devops
Classifier: Development Status :: 4 - Beta
Classifier: Intended Audience :: Developers
Classifier: Intended Audience :: System Administrators
Classifier: Programming Language :: Python :: 3
Classifier: Programming Language :: Python :: 3.11
Classifier: Programming Language :: Python :: 3.12
Classifier: Topic :: Software Development :: Code Generators
Classifier: Topic :: System :: Systems Administration
Requires-Python: >=3.11
License-File: LICENSE
Requires-Dist: typer>=0.9.0
Requires-Dist: ruamel.yaml>=0.18.0
Requires-Dist: jinja2>=3.1.0
Requires-Dist: jsonschema>=4.20.0
Requires-Dist: rich>=13.0.0
Provides-Extra: dev
Requires-Dist: pytest>=7.4.0; extra == "dev"
Requires-Dist: pytest-cov>=4.1.0; extra == "dev"
Dynamic: license-file
